maldatagen/__init__.py
maldatagen/main.py
maldatagen/plots.py
maldatagen/plots_svm.py
maldatagen/run_campaign_sbseg.py
maldatagen/engine/__init__.py
maldatagen/engine/activations/Activations.py
maldatagen/engine/activations/CeLU.py
maldatagen/engine/activations/ELU.py
maldatagen/engine/activations/Exponential.py
maldatagen/engine/activations/GELU.py
maldatagen/engine/activations/GLU.py
maldatagen/engine/activations/HardSigmoid.py
maldatagen/engine/activations/LeakyRelu.py
maldatagen/engine/activations/Linear.py
maldatagen/engine/activations/LogSigmoid.py
maldatagen/engine/activations/PReLU.py
maldatagen/engine/activations/ReLU.py
maldatagen/engine/activations/SELU.py
maldatagen/engine/activations/Sigmoid.py
maldatagen/engine/activations/SoftSign.py
maldatagen/engine/activations/Softmax.py
maldatagen/engine/activations/Softplus.py
maldatagen/engine/activations/Swish.py
maldatagen/engine/activations/Tanh.py
maldatagen/engine/activations/__init__.py
maldatagen/engine/algorithms/__init__.py
maldatagen/engine/algorithms/Adversarial/AdversarialAlgorithm.py
maldatagen/engine/algorithms/Adversarial/__init__.py
maldatagen/engine/algorithms/Autoencoder/AutoencoderAlgorithm.py
maldatagen/engine/algorithms/Autoencoder/__init__.py
maldatagen/engine/algorithms/Copy/CopyAlgorithm.py
maldatagen/engine/algorithms/Copy/__init__.py
maldatagen/engine/algorithms/DenoisingDiffusion/AlgorithmDenoisingDiffusion.py
maldatagen/engine/algorithms/DenoisingDiffusion/GaussianDenoisingDiffusion.py
maldatagen/engine/algorithms/DenoisingDiffusion/__init__.py
maldatagen/engine/algorithms/LatentDiffusion/AlgorithmLatentDiffusion.py
maldatagen/engine/algorithms/LatentDiffusion/AlgorithmVAELatentDiffusion.py
maldatagen/engine/algorithms/LatentDiffusion/GaussianLatentDiffusion.py
maldatagen/engine/algorithms/LatentDiffusion/__init__.py
maldatagen/engine/algorithms/QuantizedVAE/AlgorithmQuantizedVAE.py
maldatagen/engine/algorithms/QuantizedVAE/__init__.py
maldatagen-0.1.1.dist-info/licenses/LICENSE
maldatagen-0.1.1.dist-info/METADATA
maldatagen-0.1.1.dist-info/WHEEL
maldatagen-0.1.1.dist-info/top_level.txt
maldatagen-0.1.1.dist-info/RECORD
