Metadata-Version: 2.4
Name: maldatagen
Version: 0.1.1
Summary: MalDataGen - Tabular Data Generator
Author-email: Kayuã <kayuaolequesp@gmail.com>
License: MIT
Requires-Python: >=3.8
License-File: LICENSE
Requires-Dist: absl-py>=1.4.0
Requires-Dist: astunparse>=1.6.3
Requires-Dist: pyfiglet
Requires-Dist: cachetools>=5.3.1
Requires-Dist: certifi>=2023.7.22
Requires-Dist: charset-normalizer>=3.2.0
Requires-Dist: contourpy>=1.1.0
Requires-Dist: cycler>=0.11.0
Requires-Dist: flatbuffers>=1.12
Requires-Dist: fonttools>=4.41.1
Requires-Dist: gast>=0.4.0
Requires-Dist: google-auth>=2.22.0
Requires-Dist: google-auth-oauthlib>=0.4.6
Requires-Dist: google-pasta>=0.2.0
Requires-Dist: grpcio>=1.56.2
Requires-Dist: h5py>=3.9.0
Requires-Dist: idna>=3.4
Requires-Dist: importlib-metadata>=6.8.0; python_version < "3.10"
Requires-Dist: importlib-resources>=6.0.0; python_version < "3.10"
Requires-Dist: joblib>=1.3.1
Requires-Dist: kaleido>=0.2.1
Requires-Dist: keras>=2.9.0
Requires-Dist: keras-preprocessing>=1.1.2
Requires-Dist: kiwisolver>=1.4.4
Requires-Dist: libclang>=16.0.6
Requires-Dist: markdown>=3.4.4
Requires-Dist: markupsafe>=2.1.3
Requires-Dist: matplotlib>=3.7.2
Requires-Dist: numpy<2.0.0,>=1.21.5
Requires-Dist: numpy<1.25.0,>=1.21.5; python_version < "3.9"
Requires-Dist: oauthlib>=3.2.2
Requires-Dist: opt-einsum>=3.3.0
Requires-Dist: packaging>=23.1
Requires-Dist: pandas>=2.0.0
Requires-Dist: pillow>=10.0.0
Requires-Dist: plotly>=5.0.0
Requires-Dist: protobuf<4.0.0,>=3.19.6
Requires-Dist: pyasn1>=0.5.0
Requires-Dist: pyasn1-modules>=0.3.0
Requires-Dist: pyparsing>=3.0.9
Requires-Dist: python-dateutil>=2.8.2
Requires-Dist: pytz>=2023.3
Requires-Dist: requests>=2.31.0
Requires-Dist: requests-oauthlib>=1.3.1
Requires-Dist: rsa>=4.9
Requires-Dist: scikit-learn>=1.1.1
Requires-Dist: scipy<2.0.0,>=1.10.1
Requires-Dist: setuptools>=68.0.0
Requires-Dist: six>=1.16.0
Requires-Dist: tenacity>=8.2.2
Requires-Dist: tensorboard>=2.9.1
Requires-Dist: tensorboard-data-server>=0.6.1
Requires-Dist: tensorboard-plugin-wit>=1.8.1
Requires-Dist: tensorflow<3.0.0,>=2.9.1
Requires-Dist: tensorflow-estimator>=2.9.0
Requires-Dist: tensorflow-io-gcs-filesystem>=0.32.0
Requires-Dist: termcolor>=2.3.0
Requires-Dist: threadpoolctl>=3.2.0
Requires-Dist: typing-extensions>=4.7.1
Requires-Dist: urllib3>=1.26.16
Requires-Dist: werkzeug<2.4.0,>=2.3.6; python_version < "3.9"
Requires-Dist: werkzeug>=2.3.6
Requires-Dist: wheel>=0.41.0
Requires-Dist: wrapt>=1.15.0
Requires-Dist: zipp>=3.16.2; python_version < "3.10"
Requires-Dist: xgboost<2.1.0,>=2.0.3; python_version < "3.9"
Requires-Dist: aim>=3.17.5
Requires-Dist: mlflow>=2.12.1
Requires-Dist: neptune>=1.10.2
Requires-Dist: xgboost>=2.0.3
Requires-Dist: seaborn>=0.12.0
Requires-Dist: sdv>=1.2.1
Requires-Dist: gputil==1.4.0
Requires-Dist: psutil==5.9.5
Dynamic: license-file
